setup.py
tapioca_meetup/__init__.py
tapioca_meetup/resource_mapping.py
tapioca_meetup/tapioca_meetup.py
tapioca_meetup.egg-info/PKG-INFO
tapioca_meetup.egg-info/SOURCES.txt
tapioca_meetup.egg-info/dependency_links.txt
tapioca_meetup.egg-info/not-zip-safe
tapioca_meetup.egg-info/requires.txt
tapioca_meetup.egg-info/top_level.txt