Metadata-Version: 1.1
Name: tapioca-meetup
Version: 0.1
Summary: Meetup API wrapper using tapioca
Home-page: https://github.com/lightstrike/tapioca-meetup
Author: Geoffrey Sechter
Author-email: geoffrey.sechter@gmail.com
License: MIT
Keywords: meetup
Platform: UNKNOWN
Classifier: Development Status :: 5 - Production/Stable
Classifier: Intended Audience :: Developers
Classifier: License :: OSI Approved :: MIT License
Classifier: Natural Language :: English
Classifier: Programming Language :: Python :: 2
Classifier: Programming Language :: Python :: 2.7
Classifier: Programming Language :: Python :: 3
Classifier: Programming Language :: Python :: 3.1
Classifier: Programming Language :: Python :: 3.2
Classifier: Programming Language :: Python :: 3.3
Classifier: Programming Language :: Python :: 3.4
